leetcode/__init__.py
leetcode/array.py
leetcode/list.py
leetcode/reporter.py
leetcode/simple_drawer.py
leetcode/tree.py
leetcode_helper-0.1.2.dist-info/LICENSE
leetcode_helper-0.1.2.dist-info/METADATA
leetcode_helper-0.1.2.dist-info/WHEEL
leetcode_helper-0.1.2.dist-info/top_level.txt
leetcode_helper-0.1.2.dist-info/RECORD
